<?xml version="1.0" encoding="utf-8" ?>
<dwsync>
<file name="xaut.gif" server="//stcloudstate/users/j/jj2952us/Webspace/" local="129072795900000000" remote="129072759900000000" Dst="2" />
<file name="User.ini" server="//stcloudstate/users/j/jj2952us/Webspace/" local="127882395187556250" remote="127882359180000000" Dst="2" />
<file name="update.ini" server="//stcloudstate/users/j/jj2952us/Webspace/" local="127495891900000000" remote="127495855900000000" Dst="2" />
<file name="Uninstall PokerStars.LNK" server="//stcloudstate/users/j/jj2952us/Webspace/" local="131281099688299426" remote="131281063680000000" Dst="2" />
<file name="trace.ini" server="//stcloudstate/users/j/jj2952us/Webspace/" local="127203859120000000" remote="127203823120000000" Dst="2" />
<file name="servercert" server="//stcloudstate/users/j/jj2952us/Webspace/" local="127802860462170094" remote="127802824460000000" Dst="2" />
<file name="scsulogo.jpg" server="//stcloudstate/users/j/jj2952us/Webspace/" local="130967654196216201" remote="130967618190000000" Dst="2" />
<file name="PokerStarsUpdate.log.1" server="//stcloudstate/users/j/jj2952us/Webspace/" local="127881512953887350" remote="127881476950000000" Dst="2" />
<file name="PokerStarsUpdate.log.0" server="//stcloudstate/users/j/jj2952us/Webspace/" local="127882386055212500" remote="127882350050000000" Dst="2" />
<file name="PokerStarsCommunicate.exe" server="//stcloudstate/users/j/jj2952us/Webspace/" local="127876393913902600" remote="127876357910000000" Dst="2" />
<file name="PokerStars.log.1" server="//stcloudstate/users/j/jj2952us/Webspace/" local="127881517453887350" remote="127881481450000000" Dst="2" />
<file name="PokerStars.log.0" server="//stcloudstate/users/j/jj2952us/Webspace/" local="127882395192712500" remote="127882359190000000" Dst="2" />
<file name="PokerStars.INI" server="//stcloudstate/users/j/jj2952us/Webspace/" local="127869467132862000" remote="127869431130000000" Dst="2" />
<file name="PokerStars.exe" server="//stcloudstate/users/j/jj2952us/Webspace/" local="127876393947496350" remote="127876357940000000" Dst="2" />
<file name="NSA_header.jpg" server="//stcloudstate/users/j/jj2952us/Webspace/" local="129023722870000000" remote="129023686870000000" Dst="2" />
<file name="LinkedIn.jpg" server="//stcloudstate/users/j/jj2952us/Webspace/" local="131281099637130770" remote="131281063630000000" Dst="2" />
<file name="JimChen2008.jpg" server="//stcloudstate/users/j/jj2952us/Webspace/" local="128480952969587500" remote="128480916960000000" Dst="2" />
<file name="InfoSec.jpg" server="//stcloudstate/users/j/jj2952us/Webspace/" local="129701780495502102" remote="129701744490000000" Dst="2" />
<file name="Chen2010.jpg" server="//stcloudstate/users/j/jj2952us/Webspace/" local="129072783942621797" remote="129072747940000000" Dst="2" />
<file name="_updcache.dat" server="//stcloudstate/users/j/jj2952us/Webspace/" local="127882386059743750" remote="127882350050000000" Dst="2" />
<file name="_update2gf.dat" server="//stcloudstate/users/j/jj2952us/Webspace/" local="127876393683121350" remote="127876357680000000" Dst="2" />
<file name="_update2g.dat" server="//stcloudstate/users/j/jj2952us/Webspace/" local="127833275968105032" remote="127833239960000000" Dst="2" />
<file name="_update2def.dat" server="//stcloudstate/users/j/jj2952us/Webspace/" local="127794260015516142" remote="127794224010000000" Dst="2" />
<file name="bg380.gif" server="//stcloudstate/users/j/jj2952us/Webspace/" local="126985300200000000" remote="126985300200000000" Dst="2" />
<file name="star.gif" server="//stcloudstate/users/j/jj2952us/Webspace/" local="126985300800000000" remote="126985300800000000" Dst="2" />
<file name="otnlogo.gif" server="//stcloudstate/users/j/jj2952us/Webspace/" local="127026882600000000" remote="127026882600000000" Dst="2" />
<file name="oracle_icon.gif" server="//stcloudstate/users/j/jj2952us/Webspace/" local="127026888000000000" remote="127026888000000000" Dst="2" />
<file name="oai_OAI.gif" server="//stcloudstate/users/j/jj2952us/Webspace/" local="127026890400000000" remote="127026890400000000" Dst="2" />
<file name="Oracle_Certif.gif" server="//stcloudstate/users/j/jj2952us/Webspace/" local="127026891600000000" remote="127026891600000000" Dst="2" />
</dwsync>